{
  "$schema": "https://ui.shadcn.com/schema/registry.json",
  "name": "Shadcn Admin Kit",
  "homepage": "https://github.com/marmelab/shadcn-admin-kit",
  "items": [
    {
      "name": "shadcn-admin-kit-base",
      "type": "registry:block",
      "title": "Shadcn Admin Kit Base",
      "description": "Shadcn Admin Kit Base Components",
      "registryDependencies": [
        "alert",
        "avatar",
        "badge",
        "button",
        "card",
        "checkbox",
        "command",
        "dropdown-menu",
        "form",
        "input",
        "label",
        "navigation-menu",
        "pagination",
        "popover",
        "select",
        "separator",
        "sheet",
        "sidebar",
        "skeleton",
        "sonner",
        "table",
        "tooltip"
      ],
      "dependencies": [
        "ra-core",
        "ra-language-english",
        "ra-i18n-polyglot",
        "react-router-dom",
        "react-hook-form",
        "lodash",
        "@tanstack/react-query",
        "lucide-react",
        "inflection",
        "clsx",
        "tailwind-merge"
      ],
      "files": [
        {
          "path": "src/components/Admin.tsx",
          "type": "registry:component"
        },
        {
          "path": "src/components/Layout.tsx",
          "type": "registry:component"
        },
        {
          "path": "src/components/LoginPage.tsx",
          "type": "registry:component"
        },
        {
          "path": "src/components/AppSidebar.tsx",
          "type": "registry:component"
        },
        {
          "path": "src/components/UserMenu.tsx",
          "type": "registry:component"
        },
        {
          "path": "src/components/ThemeProvider.tsx",
          "type": "registry:component"
        },
        {
          "path": "src/components/ThemeModeToggle.tsx",
          "type": "registry:component"
        },
        {
          "path": "src/components/AutocompleteInput.tsx",
          "type": "registry:component"
        },
        {
          "path": "src/components/BadgeField.tsx",
          "type": "registry:component"
        },
        {
          "path": "src/components/Breadcrumb.tsx",
          "type": "registry:component"
        },
        {
          "path": "src/components/DataTable.tsx",
          "type": "registry:component"
        },
        {
          "path": "src/components/FormError.tsx",
          "type": "registry:component"
        },
        {
          "path": "src/components/TextInput.tsx",
          "type": "registry:component"
        },
        {
          "path": "src/components/ReferenceField.tsx",
          "type": "registry:component"
        },
        {
          "path": "src/components/ReferenceInput.tsx",
          "type": "registry:component"
        },
        {
          "path": "src/components/ReferenceManyCount.tsx",
          "type": "registry:component"
        },
        {
          "path": "src/components/List.tsx",
          "type": "registry:component"
        },
        {
          "path": "src/components/ListPagination.tsx",
          "type": "registry:component"
        },
        {
          "path": "src/components/Edit.tsx",
          "type": "registry:component"
        },
        {
          "path": "src/components/SimpleForm.tsx",
          "type": "registry:component"
        },
        {
          "path": "src/components/EditButton.tsx",
          "type": "registry:component"
        },
        {
          "path": "src/components/Create.tsx",
          "type": "registry:component"
        },
        {
          "path": "src/components/CreateButton.tsx",
          "type": "registry:component"
        },
        {
          "path": "src/components/Show.tsx",
          "type": "registry:component"
        },
        {
          "path": "src/components/ShowButton.tsx",
          "type": "registry:component"
        },
        {
          "path": "src/components/SimpleShowLayout.tsx",
          "type": "registry:component"
        },
        {
          "path": "src/components/TextField.tsx",
          "type": "registry:component"
        },
        {
          "path": "src/components/ListGuesser.tsx",
          "type": "registry:component"
        },
        {
          "path": "src/components/ShowGuesser.tsx",
          "type": "registry:component"
        },
        {
          "path": "src/components/EditGuesser.tsx",
          "type": "registry:component"
        },
        {
          "path": "src/components/Notification.tsx",
          "type": "registry:component"
        },
        {
          "path": "src/components/BulkActionsToolbar.tsx",
          "type": "registry:component"
        },
        {
          "path": "src/components/BulkDeleteButton.tsx",
          "type": "registry:component"
        },
        {
          "path": "src/components/DeleteButton.tsx",
          "type": "registry:component"
        },
        {
          "path": "src/components/ExportButton.tsx",
          "type": "registry:component"
        },
        {
          "path": "src/components/ArrayField.tsx",
          "type": "registry:component"
        },
        {
          "path": "src/components/SingleFieldList.tsx",
          "type": "registry:component"
        },
        {
          "path": "src/components/LocalesMenuButton.tsx",
          "type": "registry:component"
        },
        {
          "path": "src/components/RecordField.tsx",
          "type": "registry:component"
        },
        {
          "path": "src/lib/utils.ts",
          "type": "registry:lib"
        },
        {
          "path": "src/lib/i18nProvider.ts",
          "type": "registry:lib"
        }
      ]
    }
  ]
}
